{
  "__inputs": [
    {
      "name": "DS_PROMETHEUS",
      "label": "Prometheus",
      "description": "",
      "type": "datasource",
      "pluginId": "prometheus",
      "pluginName": "Prometheus"
    }
  ],
  "__requires": [
    {
      "type": "panel",
      "id": "gauge",
      "name": "Gauge",
      "version": ""
    },
    {
      "type": "grafana",
      "id": "grafana",
      "name": "Grafana",
      "version": "7.3.10"
    },
    {
      "type": "panel",
      "id": "graph",
      "name": "Graph",
      "version": ""
    },
    {
      "type": "datasource",
      "id": "prometheus",
      "name": "Prometheus",
      "version": "1.0.0"
    },
    {
      "type": "panel",
      "id": "stat",
      "name": "Stat",
      "version": ""
    }
  ],
  "annotations": {
    "list": [
      {
        "builtIn": 1,
        "datasource": "-- Grafana --",
        "enable": true,
        "hide": true,
        "iconColor": "rgba(0, 211, 255, 1)",
        "name": "Annotations & Alerts",
        "type": "dashboard"
      }
    ]
  },
  "editable": true,
  "gnetId": null,
  "graphTooltip": 0,
  "id": null,
  "iteration": 1630562614928,
  "links": [],
  "panels": [
    {
      "collapsed": false,
      "datasource": "Prometheus",
      "gridPos": {
        "h": 1,
        "w": 24,
        "x": 0,
        "y": 0
      },
      "id": 22,
      "panels": [],
      "title": "Memory",
      "type": "row"
    },
    {
      "datasource": "Prometheus",
      "description": "The total amount of real/physical memory installed on this host",
      "fieldConfig": {
        "defaults": {
          "custom": {},
          "mappings": [],
          "thresholds": {
            "mode": "absolute",
            "steps": [
              {
                "color": "green",
                "value": null
              }
            ]
          },
          "unit": "deckbytes"
        },
        "overrides": []
      },
      "gridPos": {
        "h": 8,
        "w": 12,
        "x": 0,
        "y": 1
      },
      "id": 16,
      "options": {
        "colorMode": "value",
        "graphMode": "none",
        "justifyMode": "auto",
        "orientation": "auto",
        "reduceOptions": {
          "calcs": [
            "mean"
          ],
          "fields": "",
          "values": false
        },
        "text": {},
        "textMode": "value"
      },
      "pluginVersion": "7.3.10",
      "targets": [
        {
          "exemplar": true,
          "expr": "memTotalReal{service=\"$node\"}",
          "interval": "",
          "legendFormat": "",
          "refId": "A"
        }
      ],
      "timeFrom": null,
      "timeShift": null,
      "title": "Total memory",
      "type": "stat"
    },
    {
      "aliasColors": {},
      "bars": false,
      "dashLength": 10,
      "dashes": false,
      "datasource": "Prometheus",
      "description": "The amount of real/physical memory currently unused or available",
      "fieldConfig": {
        "defaults": {
          "custom": {}
        },
        "overrides": []
      },
      "fill": 1,
      "fillGradient": 0,
      "gridPos": {
        "h": 8,
        "w": 12,
        "x": 12,
        "y": 1
      },
      "hiddenSeries": false,
      "id": 18,
      "legend": {
        "avg": false,
        "current": false,
        "max": false,
        "min": false,
        "show": true,
        "total": false,
        "values": false
      },
      "lines": true,
      "linewidth": 1,
      "nullPointMode": "null",
      "options": {
        "alertThreshold": true
      },
      "percentage": false,
      "pluginVersion": "7.3.10",
      "pointradius": 2,
      "points": false,
      "renderer": "flot",
      "seriesOverrides": [],
      "spaceLength": 10,
      "stack": false,
      "steppedLine": false,
      "targets": [
        {
          "expr": "memAvailReal{service=\"$node\"}",
          "interval": "",
          "legendFormat": "",
          "refId": "A"
        }
      ],
      "thresholds": [],
      "timeFrom": null,
      "timeRegions": [],
      "timeShift": null,
      "title": "Available memory",
      "tooltip": {
        "shared": true,
        "sort": 0,
        "value_type": "individual"
      },
      "type": "graph",
      "xaxis": {
        "buckets": null,
        "mode": "time",
        "name": null,
        "show": true,
        "values": []
      },
      "yaxes": [
        {
          "$$hashKey": "object:379",
          "format": "deckbytes",
          "label": null,
          "logBase": 1,
          "max": null,
          "min": null,
          "show": true
        },
        {
          "$$hashKey": "object:380",
          "format": "short",
          "label": null,
          "logBase": 1,
          "max": null,
          "min": null,
          "show": true
        }
      ],
      "yaxis": {
        "align": false,
        "alignLevel": null
      }
    },
    {
      "collapsed": false,
      "datasource": "Prometheus",
      "gridPos": {
        "h": 1,
        "w": 24,
        "x": 0,
        "y": 9
      },
      "id": 20,
      "panels": [],
      "title": "CPU",
      "type": "row"
    },
    {
      "aliasColors": {},
      "bars": false,
      "dashLength": 10,
      "dashes": false,
      "datasource": "Prometheus",
      "description": "The percentage of CPU time spent processing system-level code, calculated over the last minute",
      "fieldConfig": {
        "defaults": {
          "custom": {},
          "unit": "percent"
        },
        "overrides": []
      },
      "fill": 1,
      "fillGradient": 0,
      "gridPos": {
        "h": 8,
        "w": 12,
        "x": 0,
        "y": 10
      },
      "hiddenSeries": false,
      "id": 12,
      "legend": {
        "avg": false,
        "current": false,
        "max": false,
        "min": false,
        "show": true,
        "total": false,
        "values": false
      },
      "lines": true,
      "linewidth": 1,
      "nullPointMode": "null",
      "options": {
        "alertThreshold": true
      },
      "percentage": false,
      "pluginVersion": "7.3.10",
      "pointradius": 2,
      "points": false,
      "renderer": "flot",
      "seriesOverrides": [],
      "spaceLength": 10,
      "stack": false,
      "steppedLine": false,
      "targets": [
        {
          "expr": "ssCpuSystem{service=\"$node\"}",
          "interval": "",
          "legendFormat": "",
          "refId": "A"
        }
      ],
      "thresholds": [],
      "timeFrom": null,
      "timeRegions": [],
      "timeShift": null,
      "title": "System CPU",
      "tooltip": {
        "shared": true,
        "sort": 0,
        "value_type": "individual"
      },
      "type": "graph",
      "xaxis": {
        "buckets": null,
        "mode": "time",
        "name": null,
        "show": true,
        "values": []
      },
      "yaxes": [
        {
          "$$hashKey": "object:434",
          "format": "percent",
          "label": null,
          "logBase": 1,
          "max": null,
          "min": null,
          "show": true
        },
        {
          "$$hashKey": "object:435",
          "format": "short",
          "label": null,
          "logBase": 1,
          "max": null,
          "min": null,
          "show": true
        }
      ],
      "yaxis": {
        "align": false,
        "alignLevel": null
      }
    },
    {
      "aliasColors": {},
      "bars": false,
      "dashLength": 10,
      "dashes": false,
      "datasource": "Prometheus",
      "description": "The percentage of CPU time spent processing user-level code, calculated over the last minute",
      "fieldConfig": {
        "defaults": {
          "custom": {}
        },
        "overrides": []
      },
      "fill": 1,
      "fillGradient": 0,
      "gridPos": {
        "h": 8,
        "w": 12,
        "x": 12,
        "y": 10
      },
      "hiddenSeries": false,
      "id": 10,
      "legend": {
        "avg": false,
        "current": false,
        "max": false,
        "min": false,
        "show": true,
        "total": false,
        "values": false
      },
      "lines": true,
      "linewidth": 1,
      "nullPointMode": "null",
      "options": {
        "alertThreshold": true
      },
      "percentage": false,
      "pluginVersion": "7.3.10",
      "pointradius": 2,
      "points": false,
      "renderer": "flot",
      "seriesOverrides": [],
      "spaceLength": 10,
      "stack": false,
      "steppedLine": false,
      "targets": [
        {
          "expr": "ssCpuUser{service=\"$node\"}",
          "interval": "",
          "legendFormat": "",
          "refId": "A"
        }
      ],
      "thresholds": [],
      "timeFrom": null,
      "timeRegions": [],
      "timeShift": null,
      "title": "User CPU",
      "tooltip": {
        "shared": true,
        "sort": 0,
        "value_type": "individual"
      },
      "type": "graph",
      "xaxis": {
        "buckets": null,
        "mode": "time",
        "name": null,
        "show": true,
        "values": []
      },
      "yaxes": [
        {
          "$$hashKey": "object:542",
          "format": "percent",
          "label": null,
          "logBase": 1,
          "max": null,
          "min": null,
          "show": true
        },
        {
          "$$hashKey": "object:543",
          "format": "short",
          "label": null,
          "logBase": 1,
          "max": null,
          "min": null,
          "show": true
        }
      ],
      "yaxis": {
        "align": false,
        "alignLevel": null
      }
    },
    {
      "aliasColors": {},
      "bars": false,
      "dashLength": 10,
      "dashes": false,
      "datasource": "Prometheus",
      "description": "The percentage of processor time spent idle, calculated over the last minute",
      "fieldConfig": {
        "defaults": {
          "custom": {}
        },
        "overrides": []
      },
      "fill": 1,
      "fillGradient": 0,
      "gridPos": {
        "h": 8,
        "w": 12,
        "x": 12,
        "y": 18
      },
      "hiddenSeries": false,
      "id": 14,
      "legend": {
        "avg": false,
        "current": false,
        "max": false,
        "min": false,
        "show": true,
        "total": false,
        "values": false
      },
      "lines": true,
      "linewidth": 1,
      "nullPointMode": "null",
      "options": {
        "alertThreshold": true
      },
      "percentage": false,
      "pluginVersion": "7.3.10",
      "pointradius": 2,
      "points": false,
      "renderer": "flot",
      "seriesOverrides": [],
      "spaceLength": 10,
      "stack": false,
      "steppedLine": false,
      "targets": [
        {
          "expr": "ssCpuIdle{service=\"$node\"}",
          "interval": "",
          "legendFormat": "",
          "refId": "A"
        }
      ],
      "thresholds": [],
      "timeFrom": null,
      "timeRegions": [],
      "timeShift": null,
      "title": "Idle CPU",
      "tooltip": {
        "shared": true,
        "sort": 0,
        "value_type": "individual"
      },
      "type": "graph",
      "xaxis": {
        "buckets": null,
        "mode": "time",
        "name": null,
        "show": true,
        "values": []
      },
      "yaxes": [
        {
          "$$hashKey": "object:597",
          "format": "percent",
          "label": null,
          "logBase": 1,
          "max": null,
          "min": null,
          "show": true
        },
        {
          "$$hashKey": "object:598",
          "format": "short",
          "label": null,
          "logBase": 1,
          "max": null,
          "min": null,
          "show": true
        }
      ],
      "yaxis": {
        "align": false,
        "alignLevel": null
      }
    },
    {
      "collapsed": false,
      "datasource": "Prometheus",
      "gridPos": {
        "h": 1,
        "w": 24,
        "x": 0,
        "y": 26
      },
      "id": 24,
      "panels": [],
      "title": "Sensors",
      "type": "row"
    },
    {
      "datasource": "Prometheus",
      "description": "This is PSU1 temperature",
      "fieldConfig": {
        "defaults": {
          "color": {
            "mode": "thresholds"
          },
          "custom": {},
          "mappings": [],
          "max": 75,
          "min": 5,
          "thresholds": {
            "mode": "absolute",
            "steps": [
              {
                "color": "green",
                "value": null
              },
              {
                "color": "#EAB839",
                "value": 55
              },
              {
                "color": "red",
                "value": 65
              }
            ]
          },
          "unit": "celsius"
        },
        "overrides": []
      },
      "gridPos": {
        "h": 8,
        "w": 12,
        "x": 0,
        "y": 27
      },
      "id": 26,
      "options": {
        "reduceOptions": {
          "calcs": [
            "lastNotNull"
          ],
          "fields": "",
          "values": false
        },
        "showThresholdLabels": false,
        "showThresholdMarkers": true,
        "text": {}
      },
      "pluginVersion": "7.3.10",
      "targets": [
        {
          "exemplar": true,
          "expr": "(psu1TempOrAmbientTemp{service=\"$node\"})/10",
          "format": "heatmap",
          "interval": "",
          "legendFormat": "",
          "refId": "A"
        },
        {
          "refId": "B"
        }
      ],
      "title": "PSU1 Temperature",
      "type": "gauge"
    },
    {
      "datasource": "Prometheus",
      "description": "This is PSU2 temperature",
      "fieldConfig": {
        "defaults": {
          "color": {
            "mode": "thresholds"
          },
          "custom": {},
          "mappings": [],
          "max": 75,
          "min": 5,
          "thresholds": {
            "mode": "absolute",
            "steps": [
              {
                "color": "green",
                "value": null
              },
              {
                "color": "#EAB839",
                "value": 55
              },
              {
                "color": "red",
                "value": 65
              }
            ]
          },
          "unit": "celsius"
        },
        "overrides": []
      },
      "gridPos": {
        "h": 8,
        "w": 12,
        "x": 12,
        "y": 27
      },
      "id": 44,
      "options": {
        "reduceOptions": {
          "calcs": [
            "lastNotNull"
          ],
          "fields": "",
          "values": false
        },
        "showThresholdLabels": false,
        "showThresholdMarkers": true,
        "text": {}
      },
      "pluginVersion": "7.3.10",
      "targets": [
        {
          "exemplar": true,
          "expr": "psu2Temp{service=\"$node\"}/10",
          "format": "heatmap",
          "interval": "",
          "legendFormat": "",
          "refId": "A"
        },
        {
          "refId": "B"
        }
      ],
      "title": "PSU2 Temperature",
      "type": "gauge"
    },
    {
      "datasource": "Prometheus",
      "description": "This is cpu package temerature",
      "fieldConfig": {
        "defaults": {
          "color": {
            "mode": "thresholds"
          },
          "custom": {},
          "mappings": [],
          "max": 120,
          "min": 5,
          "thresholds": {
            "mode": "absolute",
            "steps": [
              {
                "color": "green",
                "value": null
              },
              {
                "color": "orange",
                "value": 95
              },
              {
                "color": "red",
                "value": 115
              }
            ]
          },
          "unit": "celsius"
        },
        "overrides": []
      },
      "gridPos": {
        "h": 8,
        "w": 12,
        "x": 0,
        "y": 35
      },
      "id": 30,
      "options": {
        "reduceOptions": {
          "calcs": [
            "lastNotNull"
          ],
          "fields": "",
          "values": false
        },
        "showThresholdLabels": false,
        "showThresholdMarkers": true,
        "text": {}
      },
      "pluginVersion": "7.3.10",
      "targets": [
        {
          "exemplar": true,
          "expr": "(cpuPackageSensor{service=\"$node\"})/10",
          "interval": "",
          "legendFormat": "",
          "refId": "A"
        }
      ],
      "title": "CPU Package Temperature",
      "type": "gauge"
    },
    {
      "datasource": "Prometheus",
      "description": "This is asic temperature",
      "fieldConfig": {
        "defaults": {
          "color": {
            "mode": "thresholds"
          },
          "custom": {},
          "mappings": [],
          "max": 130,
          "min": 5,
          "thresholds": {
            "mode": "absolute",
            "steps": [
              {
                "color": "green",
                "value": null
              },
              {
                "color": "orange",
                "value": 100
              },
              {
                "color": "red",
                "value": 120
              }
            ]
          },
          "unit": "celsius"
        },
        "overrides": []
      },
      "gridPos": {
        "h": 8,
        "w": 12,
        "x": 12,
        "y": 35
      },
      "id": 33,
      "options": {
        "reduceOptions": {
          "calcs": [
            "lastNotNull"
          ],
          "fields": "",
          "values": false
        },
        "showThresholdLabels": false,
        "showThresholdMarkers": true,
        "text": {}
      },
      "pluginVersion": "7.3.10",
      "targets": [
        {
          "exemplar": true,
          "expr": "asicTempSensor{service=\"$node\"}/10",
          "interval": "",
          "legendFormat": "",
          "refId": "A"
        }
      ],
      "title": "ASIC Temperature",
      "type": "gauge"
    },
    {
      "datasource": "Prometheus",
      "description": "This is cpu core sensor 0",
      "fieldConfig": {
        "defaults": {
          "color": {
            "mode": "thresholds"
          },
          "custom": {},
          "mappings": [],
          "max": 120,
          "min": 5,
          "thresholds": {
            "mode": "absolute",
            "steps": [
              {
                "color": "green",
                "value": null
              },
              {
                "color": "#EAB839",
                "value": 95
              },
              {
                "color": "red",
                "value": 115
              }
            ]
          },
          "unit": "celsius"
        },
        "overrides": []
      },
      "gridPos": {
        "h": 8,
        "w": 12,
        "x": 0,
        "y": 43
      },
      "id": 32,
      "options": {
        "reduceOptions": {
          "calcs": [
            "lastNotNull"
          ],
          "fields": "",
          "values": false
        },
        "showThresholdLabels": false,
        "showThresholdMarkers": true,
        "text": {}
      },
      "pluginVersion": "7.3.10",
      "targets": [
        {
          "exemplar": true,
          "expr": "cpuCoreSensor0{service=\"$node\"}/10",
          "interval": "",
          "legendFormat": "",
          "refId": "A"
        }
      ],
      "title": "CPU Core Sensor 0",
      "type": "gauge"
    },
    {
      "datasource": "Prometheus",
      "description": "This is cpu core sensor 1",
      "fieldConfig": {
        "defaults": {
          "color": {
            "mode": "thresholds"
          },
          "custom": {},
          "mappings": [],
          "max": 120,
          "min": 5,
          "thresholds": {
            "mode": "absolute",
            "steps": [
              {
                "color": "green",
                "value": null
              },
              {
                "color": "orange",
                "value": 95
              },
              {
                "color": "red",
                "value": 115
              }
            ]
          },
          "unit": "celsius"
        },
        "overrides": []
      },
      "gridPos": {
        "h": 8,
        "w": 12,
        "x": 12,
        "y": 43
      },
      "id": 41,
      "options": {
        "orientation": "auto",
        "reduceOptions": {
          "calcs": [
            "lastNotNull"
          ],
          "fields": "",
          "values": false
        },
        "showThresholdLabels": false,
        "showThresholdMarkers": true,
        "text": {}
      },
      "pluginVersion": "7.3.10",
      "targets": [
        {
          "exemplar": true,
          "expr": "cpuCoreSensor1{service=\"$node\"}/10",
          "interval": "",
          "legendFormat": "",
          "refId": "A"
        }
      ],
      "title": "CPU Core Sensor 1",
      "type": "gauge"
    },
    {
      "datasource": "Prometheus",
      "description": "This is port ambient sensor",
      "fieldConfig": {
        "defaults": {
          "color": {
            "mode": "thresholds"
          },
          "custom": {},
          "mappings": [],
          "max": 120,
          "min": 5,
          "thresholds": {
            "mode": "absolute",
            "steps": [
              {
                "color": "green",
                "value": null
              },
              {
                "color": "orange",
                "value": 100
              },
              {
                "color": "red",
                "value": 110
              }
            ]
          },
          "unit": "celsius"
        },
        "overrides": []
      },
      "gridPos": {
        "h": 8,
        "w": 12,
        "x": 0,
        "y": 51
      },
      "id": 42,
      "options": {
        "reduceOptions": {
          "calcs": [
            "lastNotNull"
          ],
          "fields": "",
          "values": false
        },
        "showThresholdLabels": false,
        "showThresholdMarkers": true,
        "text": {}
      },
      "pluginVersion": "7.3.10",
      "targets": [
        {
          "exemplar": true,
          "expr": "portAmbientSensor{service=\"$node\"}/10",
          "interval": "",
          "legendFormat": "",
          "refId": "A"
        }
      ],
      "title": "Port Ambient Sensor ",
      "type": "gauge"
    },
    {
      "datasource": "Prometheus",
      "description": "This is main board ambient sensor",
      "fieldConfig": {
        "defaults": {
          "color": {
            "mode": "thresholds"
          },
          "custom": {},
          "mappings": [],
          "max": 120,
          "min": 5,
          "thresholds": {
            "mode": "absolute",
            "steps": [
              {
                "color": "green",
                "value": null
              },
              {
                "color": "orange",
                "value": 100
              },
              {
                "color": "red",
                "value": 110
              }
            ]
          },
          "unit": "celsius"
        },
        "overrides": []
      },
      "gridPos": {
        "h": 8,
        "w": 12,
        "x": 12,
        "y": 51
      },
      "id": 35,
      "options": {
        "reduceOptions": {
          "calcs": [
            "lastNotNull"
          ],
          "fields": "",
          "values": false
        },
        "showThresholdLabels": false,
        "showThresholdMarkers": true,
        "text": {}
      },
      "pluginVersion": "7.3.10",
      "targets": [
        {
          "exemplar": true,
          "expr": "mainBoardAmbientSensor{service=\"$node\"}/10",
          "format": "heatmap",
          "interval": "",
          "legendFormat": "",
          "refId": "A"
        }
      ],
      "title": "Main Board Sensor ",
      "type": "gauge"
    },
    {
      "collapsed": false,
      "datasource": "Prometheus",
      "gridPos": {
        "h": 1,
        "w": 24,
        "x": 0,
        "y": 59
      },
      "id": 37,
      "panels": [],
      "title": "Interface Statistics",
      "type": "row"
    },
    {
      "aliasColors": {},
      "bars": false,
      "dashLength": 10,
      "dashes": false,
      "datasource": "Prometheus",
      "fieldConfig": {
        "defaults": {
          "color": {
            "mode": "palette-classic"
          },
          "custom": {
            "axisLabel": "",
            "axisPlacement": "auto",
            "barAlignment": 0,
            "drawStyle": "line",
            "fillOpacity": 0,
            "gradientMode": "none",
            "hideFrom": {
              "legend": false,
              "tooltip": false,
              "viz": false
            },
            "lineInterpolation": "linear",
            "lineWidth": 1,
            "pointSize": 5,
            "scaleDistribution": {
              "type": "linear"
            },
            "showPoints": "auto",
            "spanNulls": false,
            "stacking": {
              "group": "A",
              "mode": "none"
            },
            "thresholdsStyle": {
              "mode": "off"
            }
          },
          "mappings": [],
          "thresholds": {
            "mode": "absolute",
            "steps": [
              {
                "color": "green",
                "value": null
              },
              {
                "color": "red",
                "value": 80
              }
            ]
          },
          "unit": "short"
        },
        "overrides": []
      },
      "fill": 1,
      "fillGradient": 0,
      "gridPos": {
        "h": 7,
        "w": 24,
        "x": 0,
        "y": 60
      },
      "hiddenSeries": false,
      "id": 43,
      "legend": {
        "avg": false,
        "current": false,
        "max": false,
        "min": false,
        "show": true,
        "total": false,
        "values": false
      },
      "lines": true,
      "linewidth": 1,
      "nullPointMode": "null",
      "options": {
        "alertThreshold": true
      },
      "percentage": false,
      "pluginVersion": "7.3.10",
      "pointradius": 2,
      "points": false,
      "renderer": "flot",
      "seriesOverrides": [],
      "spaceLength": 10,
      "stack": false,
      "steppedLine": false,
      "targets": [
        {
          "exemplar": true,
          "expr": "irate(ifInOctets{service=\"$node\"}[10m])",
          "format": "time_series",
          "interval": "",
          "legendFormat": "{{ifAlias}}",
          "refId": "A"
        }
      ],
      "thresholds": [],
      "timeFrom": null,
      "timeRegions": [],
      "timeShift": null,
      "title": "Input Octects",
      "tooltip": {
        "shared": true,
        "sort": 0,
        "value_type": "individual"
      },
      "type": "graph",
      "xaxis": {
        "buckets": null,
        "mode": "time",
        "name": null,
        "show": true,
        "values": []
      },
      "yaxes": [
        {
          "$$hashKey": "object:86",
          "format": "short",
          "label": null,
          "logBase": 1,
          "max": null,
          "min": null,
          "show": true
        },
        {
          "$$hashKey": "object:87",
          "format": "short",
          "label": null,
          "logBase": 1,
          "max": null,
          "min": null,
          "show": true
        }
      ],
      "yaxis": {
        "align": false,
        "alignLevel": null
      }
    },
    {
      "aliasColors": {},
      "bars": false,
      "dashLength": 10,
      "dashes": false,
      "datasource": "Prometheus",
      "fieldConfig": {
        "defaults": {
          "color": {
            "mode": "palette-classic"
          },
          "custom": {
            "axisLabel": "",
            "axisPlacement": "auto",
            "barAlignment": 0,
            "drawStyle": "line",
            "fillOpacity": 0,
            "gradientMode": "none",
            "hideFrom": {
              "legend": false,
              "tooltip": false,
              "viz": false
            },
            "lineInterpolation": "linear",
            "lineWidth": 1,
            "pointSize": 5,
            "scaleDistribution": {
              "type": "linear"
            },
            "showPoints": "auto",
            "spanNulls": false,
            "stacking": {
              "group": "A",
              "mode": "none"
            },
            "thresholdsStyle": {
              "mode": "off"
            }
          },
          "mappings": [],
          "thresholds": {
            "mode": "absolute",
            "steps": [
              {
                "color": "green",
                "value": null
              },
              {
                "color": "red",
                "value": 80
              }
            ]
          }
        },
        "overrides": []
      },
      "fill": 1,
      "fillGradient": 0,
      "gridPos": {
        "h": 7,
        "w": 24,
        "x": 0,
        "y": 67
      },
      "hiddenSeries": false,
      "id": 40,
      "legend": {
        "avg": false,
        "current": false,
        "max": false,
        "min": false,
        "show": true,
        "total": false,
        "values": false
      },
      "lines": true,
      "linewidth": 1,
      "nullPointMode": "null",
      "options": {
        "alertThreshold": true
      },
      "percentage": false,
      "pluginVersion": "7.3.10",
      "pointradius": 2,
      "points": false,
      "renderer": "flot",
      "seriesOverrides": [],
      "spaceLength": 10,
      "stack": false,
      "steppedLine": false,
      "targets": [
        {
          "exemplar": true,
          "expr": "irate(ifOutOctets{service=\"$node\"}[10m])",
          "interval": "",
          "legendFormat": "{{ifIndex}}",
          "refId": "A"
        }
      ],
      "thresholds": [],
      "timeFrom": null,
      "timeRegions": [],
      "timeShift": null,
      "title": "Output Octects",
      "tooltip": {
        "shared": true,
        "sort": 0,
        "value_type": "individual"
      },
      "type": "graph",
      "xaxis": {
        "buckets": null,
        "mode": "time",
        "name": null,
        "show": true,
        "values": []
      },
      "yaxes": [
        {
          "$$hashKey": "object:203",
          "format": "short",
          "label": null,
          "logBase": 1,
          "max": null,
          "min": null,
          "show": true
        },
        {
          "$$hashKey": "object:204",
          "format": "short",
          "label": null,
          "logBase": 1,
          "max": null,
          "min": null,
          "show": true
        }
      ],
      "yaxis": {
        "align": false,
        "alignLevel": null
      }
    }
  ],
  "refresh": "",
  "schemaVersion": 26,
  "style": "dark",
  "tags": ["isf-dashboard"],
  "templating": {
    "list": [
      {
        "allValue": null,
        "current": {},
        "datasource": "Prometheus",
        "definition": "label_values(up{job=~\"snmp-exporter\"}, service)",
        "description": null,
        "error": null,
        "hide": 0,
        "includeAll": false,
        "label": "Service",
        "multi": false,
        "name": "node",
        "options": [],
        "query": "label_values(up{job=~\"snmp-exporter\"}, service)",
        "refresh": 1,
        "regex": "",
        "skipUrlSync": false,
        "sort": 0,
        "tagValuesQuery": "",
        "tags": [],
        "tagsQuery": "",
        "type": "query",
        "useTags": false
      }
    ]
  },
  "time": {
    "from": "now-15m",
    "to": "now"
  },
  "timepicker": {},
  "timezone": "",
  "title": "ISF_Network_Dashboard",
  "uid": "BbWcScZnz",
  "version": 28
}